uniplot/__init__.py
uniplot/character_sets.py
uniplot/color_themes.py
uniplot/colors.py
uniplot/conversions.py
uniplot/discretizer.py
uniplot/layer_assembly.py
uniplot/layer_factory.py
uniplot/legend_placements.py
uniplot/multi_series.py
uniplot/options.py
uniplot/param_initializer.py
uniplot/pixel_matrix.py
uniplot/plot_elements.py
uniplot/py.typed
uniplot/sections.py
uniplot/uniplot.py
uniplot/axis_labels/__init__.py
uniplot/axis_labels/datetime_label_set.py
uniplot/axis_labels/datetime_labels.py
uniplot/axis_labels/extended_talbot_labels.py
uniplot/axis_labels/label_set.py
uniplot-0.21.5.dist-info/licenses/LICENSE
uniplot-0.21.5.dist-info/METADATA
uniplot-0.21.5.dist-info/WHEEL
uniplot-0.21.5.dist-info/top_level.txt
uniplot-0.21.5.dist-info/RECORD
