Metadata-Version: 2.4
Name: uniplot
Version: 0.21.5
Summary: Lightweight plotting to the terminal. 4x resolution via Unicode.
Author-email: Olav Stetter <olav.stetter@googlemail.com>
License: Copyright (c) 2020 Olav Stetter
Project-URL: Homepage, https://github.com/olavolav/uniplot
Project-URL: Repository, https://github.com/olavolav/uniplot
Project-URL: Issues, https://github.com/olavolav/uniplot/issues
Keywords: plot,plotting,terminal,cli,console,ascii,unicode,visualization,chart,graph,data-science,machine-learning,numpy,histogram,scatter-plot,time-series,dataviz,lightweight,ci-cd,pipeline,monitoring,braille,interactive
Classifier: Development Status :: 5 - Production/Stable
Classifier: Intended Audience :: Developers
Classifier: Intended Audience :: Science/Research
Classifier: Intended Audience :: System Administrators
Classifier: Topic :: Scientific/Engineering
Classifier: Topic :: Scientific/Engineering :: Visualization
Classifier: Topic :: Software Development :: Libraries :: Python Modules
Classifier: Topic :: System :: Monitoring
Classifier: Topic :: Terminals
Classifier: License :: OSI Approved :: MIT License
Classifier: Programming Language :: Python :: 3
Classifier: Programming Language :: Python :: 3.8
Classifier: Programming Language :: Python :: 3.9
Classifier: Programming Language :: Python :: 3.10
Classifier: Programming Language :: Python :: 3.11
Classifier: Programming Language :: Python :: 3.12
Classifier: Programming Language :: Python :: 3.13
Classifier: Programming Language :: Python :: 3.14
Classifier: Operating System :: OS Independent
Classifier: Environment :: Console
Requires-Python: >=3.8
License-File: LICENSE
Requires-Dist: numpy>=1.22.0
Requires-Dist: readchar>=4.2.1
Dynamic: license-file
